neohubapi/__init__.py
neohubapi/discovery.py
neohubapi/enums.py
neohubapi/neohub.py
neohubapi/neostat.py
neohubapi-3.1.data/scripts/neohub_cli.py
neohubapi-3.1.dist-info/METADATA
neohubapi-3.1.dist-info/WHEEL
neohubapi-3.1.dist-info/top_level.txt
neohubapi-3.1.dist-info/zip-safe
neohubapi-3.1.dist-info/RECORD
