Metadata-Version: 2.4
Name: neohubapi
Version: 3.1
Summary: Async library to communicate with Heatmiser NeoHub 2 API.
Home-page: https://gitlab.com/neohubapi/neohubapi/
Author: Andrius Štikonas
Author-email: andrius@stikonas.eu
Keywords: neohub,heatmiser
Classifier: Programming Language :: Python :: 3
Classifier: License :: OSI Approved :: GNU Lesser General Public License v3 or later (LGPLv3+)
Classifier: Operating System :: OS Independent
Requires-Dist: async_property
Requires-Dist: websockets
Dynamic: author
Dynamic: author-email
Dynamic: classifier
Dynamic: description
Dynamic: description-content-type
Dynamic: home-page
Dynamic: keywords
Dynamic: requires-dist
Dynamic: summary
